_hypothesis_ftz_detector.py
_hypothesis_globals.py
_hypothesis_pytestplugin.py
hypothesis/__init__.py
hypothesis/_settings.py
hypothesis/configuration.py
hypothesis/control.py
hypothesis/core.py
hypothesis/database.py
hypothesis/entry_points.py
hypothesis/errors.py
hypothesis/provisional.py
hypothesis/py.typed
hypothesis/reporting.py
hypothesis/stateful.py
hypothesis/statistics.py
hypothesis/version.py
hypothesis/extra/__init__.py
hypothesis/extra/_array_helpers.py
hypothesis/extra/_patching.py
hypothesis/extra/array_api.py
hypothesis/extra/cli.py
hypothesis/extra/codemods.py
hypothesis/extra/dateutil.py
hypothesis/extra/dpcontracts.py
hypothesis/extra/ghostwriter.py
hypothesis/extra/lark.py
hypothesis/extra/numpy.py
hypothesis/extra/pytestplugin.py
hypothesis/extra/pytz.py
hypothesis/extra/redis.py
hypothesis/extra/django/__init__.py
hypothesis/extra/django/_fields.py
hypothesis/extra/django/_impl.py
hypothesis/extra/pandas/__init__.py
hypothesis/extra/pandas/impl.py
hypothesis/internal/__init__.py
hypothesis/internal/cache.py
hypothesis/internal/cathetus.py
hypothesis/internal/charmap.py
hypothesis/internal/compat.py
hypothesis/internal/constants_ast.py
hypothesis/internal/coverage.py
hypothesis/internal/detection.py
hypothesis/internal/entropy.py
hypothesis/internal/escalation.py
hypothesis/internal/filtering.py
hypothesis/internal/floats.py
hypothesis/internal/healthcheck.py
hypothesis/internal/intervalsets.py
hypothesis/internal/lambda_sources.py
hypothesis/internal/observability.py
hypothesis/internal/reflection.py
hypothesis/internal/scrutineer.py
hypothesis/internal/validation.py
hypothesis/internal/conjecture/__init__.py
hypothesis/internal/conjecture/choice.py
hypothesis/internal/conjecture/data.py
hypothesis/internal/conjecture/datatree.py
hypothesis/internal/conjecture/engine.py
hypothesis/internal/conjecture/floats.py
hypothesis/internal/conjecture/junkdrawer.py
hypothesis/internal/conjecture/optimiser.py
hypothesis/internal/conjecture/pareto.py
hypothesis-6.148.1.dist-info/licenses/LICENSE.txt
hypothesis-6.148.1.dist-info/METADATA
hypothesis-6.148.1.dist-info/WHEEL
hypothesis-6.148.1.dist-info/entry_points.txt
hypothesis-6.148.1.dist-info/top_level.txt
hypothesis-6.148.1.dist-info/RECORD
